{
	"format_version": "1.8.0",
	"animations": {
		"animation.weapon_1.rotation": {
			"loop": true,
			"animation_length": 1.5,
			"bones": {
				"middle": {
					"rotation": {
						"0.0": {
							"post": [0, 0, 0],
							"lerp_mode": "catmullrom"
						},
						"1.5": {
							"post": [-360, 0, 0],
							"lerp_mode": "catmullrom"
						}
					}
				}
			}
		},
		"animation.weapon_1.particle": {
			"loop": true,
			"animation_length": 0.1,
			"particle_effects": {
				"0.0": {
					"effect": "weapon_fire_1",
					"locator": "shoot1"
				},
				"0.1": {
					"effect": "weapon_fire_1",
					"locator": "shoot1"
				}
			}
		},
		"animation.weapon_1.particle.1st": {
			"loop": true,
			"animation_length": 0.1,
			"particle_effects": {
				"0.0": {
					"effect": "weapon_fire_1",
					"locator": "shoot1_1st"
				},
				"0.1": {
					"effect": "weapon_fire_1",
					"locator": "shoot1_1st"
				}
			}
		},
		"animation.weapon_1.idle": {
			"loop": true,
			"bones": {
				"rightArm": {
					"rotation": ["query.is_swimming ? 0.0 : -75.0 + query.target_x_rotation - this", "query.is_swimming ? 0.0 : -15 + query.target_y_rotation - this", 0],
					"position": [0, "0.25 * Math.sin(query.life_time * 100)", "0.25 * Math.sin(query.life_time * 100)"]
				},
				"leftArm": {
					"rotation": ["query.is_swimming ? 0.0 : -83.0 + query.target_x_rotation - this", "query.is_swimming ? 0.0 : 35.0 + query.target_y_rotation - this", 0],
					"position": [0, "0.25 * Math.sin(query.life_time * 100)", "0.25 * Math.sin(query.life_time * 100)"]
				},
				"body": {
					"rotation": [0, 0, 0]
				},
				"weapon": {
					"rotation": [-2.5, -15, 15],
					"position": [-2, 0, -1]
				}
			}
		},
		"animation.weapon_1.fire": {
			"loop": true,
			"bones": {
				"rightArm": {
					"rotation": ["query.is_swimming ? 0.0 : -75.0 + query.target_x_rotation - this", "query.is_swimming ? 0.0 : -15 + query.target_y_rotation - this", 0],
					"position": [0, 0, "0.5 * Math.sin(query.life_time * 1800)"]
				},
				"leftArm": {
					"rotation": [
						"query.is_swimming ? 0.0 : -83.0 + query.target_x_rotation - query.is_sneaking * 27.0 -this",
						"query.is_swimming ? 0.0 : 35.0 + query.target_y_rotation - this",
						0
					],
					"position": [0, 0, "0.5 * Math.sin(query.life_time * 1800)"]
				},
				"weapon": {
					"rotation": [-2.5, -15, 15],
					"position": [-2, 0, -1]
				}
			}
		},
		"animation.weapon_1.aim": {
			"loop": true,
			"bones": {
				"rightArm": {
					"rotation": ["query.is_swimming ? 0.0 : -60.0 + query.target_x_rotation - this", "query.is_swimming ? 0.0 : -15 + query.target_y_rotation - this", 0]
				},
				"leftArm": {
					"rotation": ["query.is_swimming ? 0.0 : -65.0 + query.target_x_rotation - this", "query.is_swimming ? 0.0 : 35.0 + query.target_y_rotation - this", 0]
				},
				"body": {
					"rotation": [0, 0, 0]
				},
				"head": {
					"rotation": [7.5, 0, -15]
				},
				"weapon": {
					"rotation": [-7.5, -30, 15],
					"position": [-1, 1, -3]
				}
			},
			"particle_effects": {
				"0.0": {
					"effect": "weapon_fire_1",
					"locator": "shoot"
				}
			}
		},
		"animation.weapon_1.aim.fire": {
			"loop": true,
			"bones": {
				"rightArm": {
					"rotation": ["query.is_swimming ? 0.0 : -60.0 + query.target_x_rotation - this", "query.is_swimming ? 0.0 : -15 + query.target_y_rotation - this", 0],
					"position": [0, 0, "0.5 * Math.sin(query.life_time * 1800)"]
				},
				"leftArm": {
					"rotation": ["query.is_swimming ? 0.0 : -65.0 + query.target_x_rotation - this", "query.is_swimming ? 0.0 : 35.0 + query.target_y_rotation - this", 0],
					"position": [0, 0, "0.5 * Math.sin(query.life_time * 1800)"]
				},
				"body": {
					"rotation": [0, 0, 0]
				},
				"head": {
					"rotation": [7.5, 0, -15]
				},
				"weapon": {
					"rotation": [-7.5, -30, 15],
					"position": [-1, 1, -3]
				}
			}
		},
		"animation.weapon_1.loading": {
			"loop": "hold_on_last_frame",
			"animation_length": 2,
			"bones": {
				"rightArm": {
					"rotation": {
						"0.0": [-75, -15, 0],
						"0.0833": {
							"pre": [-105, -15, 0],
							"post": [-105, -15, 0],
							"lerp_mode": "catmullrom"
						},
						"1.25": {
							"post": [-105, -15, 0],
							"lerp_mode": "catmullrom"
						},
						"1.5": [-75, -15, 0],
						"2.0": [-75, -15, 0]
					},
					"position": {
						"0.0": [0, 0, -1],
						"1.5": [0, 0, -1],
						"1.6667": [0, 0, 0],
						"1.8333": [0, 0, -1],
						"2.0": [0, 0, -1]
					}
				},
				"leftArm": {
					"rotation": {
						"0.0": [-83, 35, 0],
						"0.25": {
							"pre": [-100, 40, 0],
							"post": [-100, 40, 0],
							"lerp_mode": "catmullrom"
						},
						"0.5833": {
							"post": [-45, 40, 0],
							"lerp_mode": "catmullrom"
						},
						"1.0": {
							"post": [-100, 40, 0],
							"lerp_mode": "catmullrom"
						},
						"1.25": {
							"post": [-100, 40, 0],
							"lerp_mode": "catmullrom"
						},
						"1.5": [-83, 35, 0],
						"2.0": [-83, 35, 0]
					},
					"position": {
						"0.25": {
							"pre": [0, 0, 0],
							"post": [0, 0, 0],
							"lerp_mode": "catmullrom"
						},
						"1.0": {
							"post": [0, 0, 0],
							"lerp_mode": "catmullrom"
						},
						"1.25": {
							"post": [0, 0, 0],
							"lerp_mode": "catmullrom"
						},
						"1.5": {
							"post": [0, 0, 0],
							"lerp_mode": "catmullrom"
						},
						"2.0": [0, 0, 0]
					}
				},
				"weapon": {
					"rotation": {
						"0.0": [-5, -15, 15],
						"0.0833": {
							"pre": [-5, -15, 0],
							"post": [-5, -15, 0],
							"lerp_mode": "catmullrom"
						},
						"0.25": [-5, -15, 0],
						"1.25": [-5, -15, 0],
						"1.5": [-5, -15, 15],
						"2.0": [-5, -15, 15]
					},
					"position": {
						"0.0": [-2, 0, -1],
						"0.0833": {
							"pre": [0, 0, -1],
							"post": [0, 0, -1],
							"lerp_mode": "catmullrom"
						},
						"0.25": [0, 0, -1],
						"1.25": [0, 0, -1],
						"1.5": [-2, 0, -1],
						"2.0": [-2, 0, -1]
					}
				},
				"reload": {
					"rotation": {
						"0.25": [0, 0, 0],
						"0.5833": [-25, 0, 0],
						"1.0": [0, 0, 0]
					},
					"position": {
						"0.25": [0, 0, 0],
						"0.5833": [10, -8, -2],
						"1.0": [0, 0, 0]
					}
				}
			}
		},
		"animation.weapon_1.walk": {
			"loop": true,
			"bones": {
				"rightArm": {
					"rotation": [-32.89913, -12.67956, -18.74227]
				},
				"leftArm": {
					"rotation": [-39.97272, -1.76749, -1.76833]
				},
				"weapon": {
					"rotation": [40.30897, 18.80651, -43.93631],
					"position": [5, 3, 7]
				}
			}
		},
		"animation.weapon_1.idle.1st": {
			"loop": true,
			"animation_length": 12,
			"bones": {
				"rightArm": {
					"rotation": {
						"8.0": [0, 0, 0],
						"8.5": {
							"pre": [2.5, 0, 0],
							"post": [2.5, 0, 0],
							"lerp_mode": "catmullrom"
						},
						"10.5": {
							"post": [2.5, 0, 0],
							"lerp_mode": "catmullrom"
						},
						"10.75": {
							"post": [-0.15842, 2.54899, -0.40429],
							"lerp_mode": "catmullrom"
						},
						"11.75": {
							"post": [-0.15842, 2.54899, -0.40429],
							"lerp_mode": "catmullrom"
						},
						"12.0": [0, 0, 0]
					},
					"position": {
						"0.0": [0, "0.25 * Math.sin(query.life_time * 100)", "0.25 * Math.sin(query.life_time * 100)"],
						"8.0": [0, 0, 0],
						"8.5": {
							"pre": [-6, 4, 7],
							"post": [-6, 4, 7],
							"lerp_mode": "catmullrom"
						},
						"10.5": {
							"post": [-6, 4, 7],
							"lerp_mode": "catmullrom"
						},
						"10.75": {
							"post": [2, 2, 10],
							"lerp_mode": "catmullrom"
						},
						"11.75": {
							"post": [2, 2, 10],
							"lerp_mode": "catmullrom"
						},
						"12.0": [0, 0, 0]
					},
					"scale": {
						"0.0": [1, 1, 1],
						"10.5": [1, 1, 1],
						"10.75": [1, 1.5, 1],
						"11.75": [1, 1.5, 1],
						"12.0": [1, 1, 1]
					}
				},
				"leftArm": {
					"rotation": {
						"0.0": [0, 0, 0],
						"8.0": [0, 0, 0],
						"8.5": {
							"pre": [11.52322, 50.14805, -23.558],
							"post": [11.52322, 50.14805, -23.558],
							"lerp_mode": "catmullrom"
						},
						"10.5": {
							"post": [11.52322, 50.14805, -23.558],
							"lerp_mode": "catmullrom"
						},
						"10.75": {
							"post": [84.02322, 50.14805, -23.558],
							"lerp_mode": "catmullrom"
						},
						"11.75": {
							"post": [84.02322, 50.14805, -23.558],
							"lerp_mode": "catmullrom"
						},
						"12.0": [0, 0, 0]
					},
					"position": {
						"0.0": [0, "0.25 * Math.sin(query.life_time * 100)", "0.25 * Math.sin(query.life_time * 100)"],
						"8.0": [0, 0, 0],
						"8.5": {
							"pre": [-4, 1.5, -7],
							"post": [-4, 1.5, -7],
							"lerp_mode": "catmullrom"
						},
						"10.5": {
							"post": [-4, 1.5, -7],
							"lerp_mode": "catmullrom"
						},
						"10.75": {
							"post": [-6, -1, -6],
							"lerp_mode": "catmullrom"
						},
						"11.75": {
							"post": [-6, -1, -6],
							"lerp_mode": "catmullrom"
						},
						"12.0": [0, 0, 0]
					},
					"scale": [1, 1.5, 1]
				},
				"weapon": {
					"rotation": {
						"0.0": [0, 0, 0],
						"8.0": [0, 0, 0],
						"8.5": {
							"pre": [-23.04151, -70.98469, -26.96476],
							"post": [-23.04151, -70.98469, -26.96476],
							"lerp_mode": "catmullrom"
						},
						"10.5": {
							"post": [-23.04151, -70.98469, -26.96476],
							"lerp_mode": "catmullrom"
						},
						"10.75": {
							"post": [93.10315, -23.30143, -4.1488],
							"lerp_mode": "catmullrom"
						},
						"11.75": {
							"post": [93.10315, -23.30143, -4.1488],
							"lerp_mode": "catmullrom"
						},
						"12.0": [0, 0, 0]
					},
					"position": {
						"0.0": [0, "0.25 * Math.sin(query.life_time * 100)", "0.25 * Math.sin(query.life_time * 100)"],
						"8.0": [0, 0, 0],
						"8.5": {
							"pre": [-10, 5, 0],
							"post": [-10, 5, 0],
							"lerp_mode": "catmullrom"
						},
						"10.5": {
							"post": [-10, 5, 0],
							"lerp_mode": "catmullrom"
						},
						"10.75": {
							"post": [-3, 2, 10],
							"lerp_mode": "catmullrom"
						},
						"11.75": {
							"post": [-3, 2, 10],
							"lerp_mode": "catmullrom"
						},
						"12.0": [0, 0, 0]
					}
				}
			}
		},
		"animation.weapon_1.fire.1st": {
			"loop": true,
			"bones": {
				"rightArm": {
					"position": [0, 0, "0.5 * Math.sin(query.life_time * 1800)"]
				},
				"leftArm": {
					"position": [0, 0, "0.5 * Math.sin(query.life_time * 1800)"],
					"scale": {
						"0.0": {
							"post": [1, 1.5, 1],
							"lerp_mode": "catmullrom"
						}
					}
				},
				"weapon": {
					"position": [0, 0, "0.5 * Math.sin(query.life_time * 1800)"]
				}
			}
		},
		"animation.weapon_1.aim.1st": {
			"loop": true,
			"bones": {
				"rightArm": {
					"rotation": {
						"0.0": {
							"post": [-1.7336, 13.34856, -18.05798],
							"lerp_mode": "catmullrom"
						}
					},
					"position": {
						"0.0": {
							"post": [-8, 5, -6],
							"lerp_mode": "catmullrom"
						}
					}
				},
				"leftArm": {
					"rotation": {
						"0.0": {
							"post": [18.25943, 12.41286, -21.8023],
							"lerp_mode": "catmullrom"
						}
					},
					"position": {
						"0.0": {
							"post": [-5, 1, -10],
							"lerp_mode": "catmullrom"
						}
					},
					"scale": {
						"0.0": {
							"post": [1, 1.5, 1],
							"lerp_mode": "catmullrom"
						}
					}
				},
				"weapon": {
					"rotation": {
						"0.0": {
							"post": [243.3, 13.4658, 243.34186],
							"lerp_mode": "catmullrom"
						}
					},
					"position": {
						"0.0": {
							"post": [-8.55, 2.65, -8],
							"lerp_mode": "catmullrom"
						}
					}
				}
			}
		},
		"animation.weapon_1.aim.fire.1st": {
			"loop": true,
			"bones": {
				"rightArm": {
					"rotation": {
						"0.0": {
							"post": [-1.7336, 13.34856, -18.05798],
							"lerp_mode": "catmullrom"
						}
					},
					"position": {
						"0.0": {
							"post": [-8.55, 2.65, "-8 + 0.5 * Math.sin(query.life_time * 1800)"],
							"lerp_mode": "catmullrom"
						}
					}
				},
				"leftArm": {
					"rotation": {
						"0.0": {
							"post": [18.25943, 12.41286, -21.8023],
							"lerp_mode": "catmullrom"
						}
					},
					"position": {
						"0.0": {
							"post": [-5, 1, "-10 + 0.5 * Math.sin(query.life_time * 1800)"],
							"lerp_mode": "catmullrom"
						}
					},
					"scale": {
						"0.0": {
							"post": [1, 1.5, 1],
							"lerp_mode": "catmullrom"
						}
					}
				},
				"weapon": {
					"rotation": {
						"0.0": {
							"post": [243.3, 13.4658, 243.34186],
							"lerp_mode": "catmullrom"
						}
					},
					"position": {
						"0.0": {
							"post": [-8.55, 2.65, "-8 + 0.5 * Math.sin(query.life_time * 1800)"],
							"lerp_mode": "catmullrom"
						}
					}
				}
			}
		},
		"animation.weapon_1.loading.1st": {
			"loop": "hold_on_last_frame",
			"animation_length": 2,
			"bones": {
				"rightArm": {
					"rotation": {
						"0.0": {
							"post": [0, 0, 0],
							"lerp_mode": "catmullrom"
						},
						"0.25": {
							"post": [-17.5, 0, 0],
							"lerp_mode": "catmullrom"
						},
						"1.25": {
							"post": [-17.5, 0, 0],
							"lerp_mode": "catmullrom"
						},
						"1.5": {
							"post": [0, 0, 0],
							"lerp_mode": "catmullrom"
						},
						"1.5833": {
							"post": [-17.5, 0, 0],
							"lerp_mode": "catmullrom"
						},
						"1.6667": {
							"post": [-17.5, 0, 0],
							"lerp_mode": "catmullrom"
						},
						"1.75": {
							"post": [-17.5, 0, 0],
							"lerp_mode": "catmullrom"
						},
						"2.0": [0, 0, 0]
					},
					"position": {
						"0.0": {
							"post": [0, 0, 0],
							"lerp_mode": "catmullrom"
						},
						"0.25": {
							"post": [1, 3, 0],
							"lerp_mode": "catmullrom"
						},
						"1.25": {
							"post": [1, 3, 0],
							"lerp_mode": "catmullrom"
						},
						"1.5": {
							"post": [0, 0, 0],
							"lerp_mode": "catmullrom"
						},
						"1.5833": {
							"post": [-2, 4, -3],
							"lerp_mode": "catmullrom"
						},
						"1.6667": {
							"post": [-2, 4, -6],
							"lerp_mode": "catmullrom"
						},
						"1.75": {
							"post": [-2, 4, -3],
							"lerp_mode": "catmullrom"
						},
						"2.0": [0, 0, 0]
					}
				},
				"leftArm": {
					"rotation": {
						"0.0": {
							"post": [0, 0, 0],
							"lerp_mode": "catmullrom"
						},
						"0.0833": {
							"post": [0, 0, 0],
							"lerp_mode": "catmullrom"
						},
						"0.25": {
							"post": [-24.08181, -8.27858, 1.43375],
							"lerp_mode": "catmullrom"
						},
						"0.3333": {
							"post": [46.04113, 9.47299, -58.01302],
							"lerp_mode": "catmullrom"
						},
						"0.8333": {
							"post": [46.04113, 9.47299, -58.01302],
							"lerp_mode": "catmullrom"
						},
						"1.0": {
							"post": [-32.37365, -20.64815, 2.86025],
							"lerp_mode": "catmullrom"
						},
						"1.25": {
							"post": [-32.37365, -20.64815, 2.86025],
							"lerp_mode": "catmullrom"
						},
						"1.5": {
							"post": [0, 0, 0],
							"lerp_mode": "catmullrom"
						},
						"2.0": [0, 0, 0]
					},
					"position": {
						"0.0": {
							"post": [0, 0, 0],
							"lerp_mode": "catmullrom"
						},
						"0.0833": {
							"post": [0, 0, 0],
							"lerp_mode": "catmullrom"
						},
						"0.25": {
							"post": [2, 1, -5],
							"lerp_mode": "catmullrom"
						},
						"0.3333": {
							"post": [-14, -8, -17],
							"lerp_mode": "catmullrom"
						},
						"0.8333": {
							"post": [-14, -8, -17],
							"lerp_mode": "catmullrom"
						},
						"1.0": {
							"post": [1, 0, -1],
							"lerp_mode": "catmullrom"
						},
						"1.25": {
							"post": [1, 0, -1],
							"lerp_mode": "catmullrom"
						},
						"1.5": {
							"post": [0, 0, 0],
							"lerp_mode": "catmullrom"
						},
						"2.0": [0, 0, 0]
					},
					"scale": {
						"0.0": {
							"post": [1, 1.5, 1],
							"lerp_mode": "catmullrom"
						},
						"0.0833": {
							"post": [1, 1.5, 1],
							"lerp_mode": "catmullrom"
						},
						"0.25": {
							"post": [1, 1.5, 1],
							"lerp_mode": "catmullrom"
						},
						"1.0": {
							"post": [1, 1.8, 1],
							"lerp_mode": "catmullrom"
						},
						"1.25": {
							"post": [1, 1.8, 1],
							"lerp_mode": "catmullrom"
						},
						"1.5": {
							"post": [1, 1.5, 1],
							"lerp_mode": "catmullrom"
						},
						"2.0": [1, 1.5, 1]
					}
				},
				"weapon": {
					"rotation": {
						"0.0": {
							"post": [0, 0, 0],
							"lerp_mode": "catmullrom"
						},
						"0.25": {
							"post": [16.63795, -26.6733, 24.18699],
							"lerp_mode": "catmullrom"
						},
						"1.25": {
							"post": [16.63795, -26.6733, 24.18699],
							"lerp_mode": "catmullrom"
						},
						"1.5": [0, 0, 0]
					},
					"position": {
						"0.0": {
							"post": [0, 0, 0],
							"lerp_mode": "catmullrom"
						},
						"0.25": {
							"post": [2, 7, -5],
							"lerp_mode": "catmullrom"
						},
						"1.25": {
							"post": [2, 7, -5],
							"lerp_mode": "catmullrom"
						},
						"1.5": [0, 0, 0],
						"2.0": [0, 0, 0]
					}
				},
				"reload": {
					"rotation": {
						"0.25": {
							"pre": [0, 0, 0],
							"post": [0, 0, 0],
							"lerp_mode": "catmullrom"
						},
						"0.3333": {
							"post": [0, 0, 0],
							"lerp_mode": "catmullrom"
						},
						"0.8333": {
							"post": [0, 0, 0],
							"lerp_mode": "catmullrom"
						},
						"1.0": [0, 0, 0]
					},
					"position": {
						"0.25": {
							"pre": [0, 0, 0],
							"post": [0, 0, 0],
							"lerp_mode": "catmullrom"
						},
						"0.3333": {
							"post": [4, -14, -19],
							"lerp_mode": "catmullrom"
						},
						"0.8333": {
							"post": [4, -14, -19],
							"lerp_mode": "catmullrom"
						},
						"1.0": [0, 0, 0]
					}
				}
			}
		},
		"animation.weapon_1.walk.1st": {
			"loop": true,
			"bones": {
				"rightArm": {
					"rotation": [-33.91359, 4.5888, -84.7813],
					"position": [-6, 7, -3]
				},
				"leftArm": {
					"rotation": [28.36539, 15.84892, 54.59465],
					"position": [-9, 7, -11],
					"scale": [1, 1.3, 1]
				},
				"weapon": {
					"rotation": [-53.36576, -37.72863, -64.40719],
					"position": [-13, -1, -7]
				}
			}
		}
	}
}