{
  "format_version": "1.20.30",
  "minecraft:item": {
    "description": {
      "identifier": "coldsink:machine_hero_weapon",
      "menu_category": {  
        "group": "itemGroup.name.arrow",  
        "category": "equipment", 
        "is_hidden_in_commands": false 
      }
    },
    "components": {
      "minecraft:max_stack_size": 1,
      "minecraft:icon": {
        "texture": "machine_hero_weapon"
      },
      "minecraft:display_name": {
        "value": "§b=< 机械重火力 >="
      },
      "minecraft:use_duration": 99999,
      "minecraft:food": {
        "can_always_eat": true
      }
    }
  }
}